{
  "abilities": [],
  "attrib": [
    {
      "display": "+ {value} Attack Range (Melee Only)",
      "key": "melee_attack_range",
      "value": "50"
    },
    {
      "display": "+ {value} Damage",
      "key": "bonus_damage",
      "value": "8"
    },
    {
      "display": "+ {value} Armor",
      "key": "bonus_armor",
      "value": "4"
    }
  ],
  "behavior": null,
  "cd": false,
  "charges": false,
  "components": null,
  "cost": 0,
  "created": false,
  "id": 355,
  "mc": false,
  "name": "Broom Handle",
  "notes": "",
  "qual": null,
  "short_name": "broom_handle"
}