{
  "abilities": [],
  "attrib": [
    {
      "display": "+ {value} Attack Speed",
      "key": "attack_speed",
      "value": "25"
    },
    {
      "display": "+ {value}% Magic Resistance",
      "key": "magic_resist",
      "value": "15"
    },
    {
      "display": "+ {value} Health",
      "key": "bonus_health",
      "value": "205"
    }
  ],
  "behavior": null,
  "cd": false,
  "charges": false,
  "components": null,
  "cost": 0,
  "created": false,
  "id": 1648,
  "mc": false,
  "name": "Dominant",
  "notes": "",
  "qual": null,
  "short_name": "enhancement_dominant"
}